PBI_dashboard_creator/__init__.py
PBI_dashboard_creator/add_ADLS_csv.py
PBI_dashboard_creator/add_background_image.py
PBI_dashboard_creator/add_button.py
PBI_dashboard_creator/add_card.py
PBI_dashboard_creator/add_local_csv.py
PBI_dashboard_creator/add_shape_map.py
PBI_dashboard_creator/add_slicer.py
PBI_dashboard_creator/add_text_box.py
PBI_dashboard_creator/add_tmdl.py
PBI_dashboard_creator/create_blank_dashboard.py
PBI_dashboard_creator/create_date_hrcy.py
PBI_dashboard_creator/create_new_chart.py
PBI_dashboard_creator/create_new_page.py
PBI_dashboard_creator/create_tmdl.py
PBI_dashboard_creator/generate_bin_measures.py
PBI_dashboard_creator/update_diagramLayout.py
PBI_dashboard_creator/update_model_file.py
PBI_dashboard_creator/dashboard_resources/.gitignore
PBI_dashboard_creator/dashboard_resources/blank_template.pbip
PBI_dashboard_creator/dashboard_resources/blank_template.Report/.platform
PBI_dashboard_creator/dashboard_resources/blank_template.Report/definition.pbir
PBI_dashboard_creator/dashboard_resources/blank_template.Report/StaticResources/SharedResources/BaseThemes/CY24SU10.json
PBI_dashboard_creator/dashboard_resources/blank_template.Report/definition/report.json
PBI_dashboard_creator/dashboard_resources/blank_template.Report/definition/version.json
PBI_dashboard_creator/dashboard_resources/blank_template.Report/definition/pages/pages.json
PBI_dashboard_creator/dashboard_resources/blank_template.Report/definition/pages/915e09e5204515bccac2/page.json
PBI_dashboard_creator/dashboard_resources/blank_template.SemanticModel/.platform
PBI_dashboard_creator/dashboard_resources/blank_template.SemanticModel/definition.pbism
PBI_dashboard_creator/dashboard_resources/blank_template.SemanticModel/diagramLayout.json
PBI_dashboard_creator/dashboard_resources/blank_template.SemanticModel/.pbi/editorSettings.json
PBI_dashboard_creator/dashboard_resources/blank_template.SemanticModel/definition/database.tmdl
pbi_dashboard_creator-1.2.0.dist-info/METADATA
pbi_dashboard_creator-1.2.0.dist-info/WHEEL
pbi_dashboard_creator-1.2.0.dist-info/licenses/LICENSE
pbi_dashboard_creator-1.2.0.dist-info/RECORD
